[{"config": {"player": {"type": "DQN8", "num_inputs": 5, "num_actions": 2, "seed": 29}, "fps": 100, "simulation_only": true, "num_episodes": 70, "paddle_size": [40, 250], "ball_size": 40, "ball_speed": 1, "screen_size": [600, 600], "start_time": 1688752562.5318348, "reward": "1 if collided else -1 if done else 0"}}, {"norm_timestamp": 0.0, "event": "game begin"}, {"norm_timestamp": 0.01876521110534668, "event": "ball bounce"}, {"norm_timestamp": 0.04226112365722656, "event": "ball bounce"}, {"norm_timestamp": 0.05443215370178223, "event": "ball return"}, {"norm_timestamp": 0.09015321731567383, "event": "ball bounce"}, {"norm_timestamp": 0.12911009788513184, "event": "ball missed"}, {"norm_timestamp": 0.12911105155944824, "event": "motor layout: 0"}, {"norm_timestamp": 0.14674615859985352, "event": "ball bounce"}, {"norm_timestamp": 0.15134215354919434, "event": "ball bounce"}, {"norm_timestamp": 0.18457531929016113, "event": "ball missed"}, {"norm_timestamp": 0.18457603454589844, "event": "motor layout: 0"}, {"norm_timestamp": 0.20203018188476562, "event": "ball bounce"}, {"norm_timestamp": 0.2396101951599121, "event": "ball missed"}, {"norm_timestamp": 0.23961114883422852, "event": "motor layout: 0"}, {"norm_timestamp": 0.25720715522766113, "event": "ball bounce"}, {"norm_timestamp": 0.2924621105194092, "event": "ball return"}, {"norm_timestamp": 0.3267781734466553, "event": "ball bounce"}, {"norm_timestamp": 0.3609771728515625, "event": "ball return"}, {"norm_timestamp": 0.3953232765197754, "event": "ball bounce"}, {"norm_timestamp": 0.4303562641143799, "event": "ball return"}, {"norm_timestamp": 0.4649820327758789, "event": "ball bounce"}, {"norm_timestamp": 0.5021650791168213, "event": "ball missed"}, {"norm_timestamp": 0.5021660327911377, "event": "motor layout: 0"}, {"norm_timestamp": 0.5192303657531738, "event": "ball bounce"}, {"norm_timestamp": 0.5317881107330322, "event": "ball bounce"}, {"norm_timestamp": 0.5537440776824951, "event": "ball return"}, {"norm_timestamp": 0.5882742404937744, "event": "ball bounce"}, {"norm_timestamp": 0.5964300632476807, "event": "ball bounce"}, {"norm_timestamp": 0.6255121231079102, "event": "ball missed"}, {"norm_timestamp": 0.6255133152008057, "event": "motor layout: 0"}, {"norm_timestamp": 0.6428391933441162, "event": "ball bounce"}, {"norm_timestamp": 0.6776142120361328, "event": "ball return"}, {"norm_timestamp": 0.7123892307281494, "event": "ball bounce"}, {"norm_timestamp": 0.7451000213623047, "event": "ball bounce"}, {"norm_timestamp": 0.749643087387085, "event": "ball missed"}, {"norm_timestamp": 0.7496440410614014, "event": "motor layout: 0"}, {"norm_timestamp": 0.7674381732940674, "event": "ball bounce"}, {"norm_timestamp": 0.7768702507019043, "event": "ball bounce"}, {"norm_timestamp": 0.8051393032073975, "event": "ball missed"}, {"norm_timestamp": 0.8051402568817139, "event": "motor layout: 0"}, {"norm_timestamp": 0.8224761486053467, "event": "ball bounce"}, {"norm_timestamp": 0.8447060585021973, "event": "ball bounce"}, {"norm_timestamp": 0.8564090728759766, "event": "ball return"}, {"norm_timestamp": 0.8902032375335693, "event": "ball bounce"}, {"norm_timestamp": 0.9269843101501465, "event": "ball missed"}, {"norm_timestamp": 0.9269852638244629, "event": "motor layout: 0"}, {"norm_timestamp": 0.9445211887359619, "event": "ball bounce"}, {"norm_timestamp": 0.9672870635986328, "event": "ball bounce"}, {"norm_timestamp": 0.9791672229766846, "event": "ball return"}, {"norm_timestamp": 1.0134739875793457, "event": "ball bounce"}, {"norm_timestamp": 1.0507261753082275, "event": "ball missed"}, {"norm_timestamp": 1.050727128982544, "event": "motor layout: 0"}, {"norm_timestamp": 1.0679872035980225, "event": "ball bounce"}, {"norm_timestamp": 1.0906450748443604, "event": "ball bounce"}, {"norm_timestamp": 1.105443000793457, "event": "ball missed"}, {"norm_timestamp": 1.1054441928863525, "event": "motor layout: 0"}, {"norm_timestamp": 1.1227471828460693, "event": "ball bounce"}, {"norm_timestamp": 1.1591479778289795, "event": "ball missed"}, {"norm_timestamp": 1.159149169921875, "event": "motor layout: 0"}, {"norm_timestamp": 1.1765611171722412, "event": "ball bounce"}, {"norm_timestamp": 1.207611083984375, "event": "ball bounce"}, {"norm_timestamp": 1.2113289833068848, "event": "ball return"}, {"norm_timestamp": 1.2457389831542969, "event": "ball bounce"}, {"norm_timestamp": 1.283041000366211, "event": "ball return"}, {"norm_timestamp": 1.3123340606689453, "event": "ball bounce"}, {"norm_timestamp": 1.3196611404418945, "event": "ball bounce"}, {"norm_timestamp": 1.357131004333496, "event": "ball missed"}, {"norm_timestamp": 1.3571319580078125, "event": "motor layout: 0"}, {"norm_timestamp": 1.3747551441192627, "event": "ball bounce"}, {"norm_timestamp": 1.412262201309204, "event": "ball missed"}, {"norm_timestamp": 1.4122631549835205, "event": "motor layout: 0"}, {"norm_timestamp": 1.4296071529388428, "event": "ball bounce"}, {"norm_timestamp": 1.446923017501831, "event": "ball bounce"}, {"norm_timestamp": 1.4638493061065674, "event": "ball return"}, {"norm_timestamp": 1.4983270168304443, "event": "ball bounce"}, {"norm_timestamp": 1.5202431678771973, "event": "ball bounce"}, {"norm_timestamp": 1.5338873863220215, "event": "ball return"}, {"norm_timestamp": 1.5690240859985352, "event": "ball bounce"}, {"norm_timestamp": 1.593675136566162, "event": "ball bounce"}, {"norm_timestamp": 1.603614330291748, "event": "ball return"}, {"norm_timestamp": 1.6375012397766113, "event": "ball bounce"}, {"norm_timestamp": 1.665964126586914, "event": "ball bounce"}, {"norm_timestamp": 1.673151969909668, "event": "ball return"}, {"norm_timestamp": 1.7081501483917236, "event": "ball bounce"}, {"norm_timestamp": 1.737407922744751, "event": "ball bounce"}, {"norm_timestamp": 1.7416961193084717, "event": "ball return"}, {"norm_timestamp": 1.7811031341552734, "event": "ball bounce"}, {"norm_timestamp": 1.8229551315307617, "event": "ball bounce"}, {"norm_timestamp": 1.8256120681762695, "event": "ball missed"}, {"norm_timestamp": 1.825613021850586, "event": "motor layout: 0"}, {"norm_timestamp": 1.8426213264465332, "event": "ball bounce"}, {"norm_timestamp": 1.8765230178833008, "event": "ball return"}, {"norm_timestamp": 1.9102661609649658, "event": "ball bounce"}, {"norm_timestamp": 1.9456391334533691, "event": "ball missed"}, {"norm_timestamp": 1.9456391334533691, "event": "motor layout: 0"}, {"norm_timestamp": 1.9620091915130615, "event": "ball bounce"}, {"norm_timestamp": 1.9956202507019043, "event": "ball return"}, {"norm_timestamp": 2.029431104660034, "event": "ball bounce"}, {"norm_timestamp": 2.0633511543273926, "event": "ball return"}, {"norm_timestamp": 2.0968470573425293, "event": "ball bounce"}, {"norm_timestamp": 2.1330761909484863, "event": "ball missed"}, {"norm_timestamp": 2.1330771446228027, "event": "motor layout: 0"}, {"norm_timestamp": 2.150052070617676, "event": "ball bounce"}, {"norm_timestamp": 2.186342239379883, "event": "ball missed"}, {"norm_timestamp": 2.186343193054199, "event": "motor layout: 0"}, {"norm_timestamp": 2.186343193054199, "event": "ball return"}, {"norm_timestamp": 2.203369140625, "event": "ball bounce"}, {"norm_timestamp": 2.2255899906158447, "event": "ball bounce"}, {"norm_timestamp": 2.2370500564575195, "event": "ball return"}, {"norm_timestamp": 2.270261287689209, "event": "ball bounce"}, {"norm_timestamp": 2.306615114212036, "event": "ball missed"}, {"norm_timestamp": 2.3066160678863525, "event": "motor layout: 0"}, {"norm_timestamp": 2.3066160678863525, "event": "ball return"}, {"norm_timestamp": 2.32362699508667, "event": "ball bounce"}, {"norm_timestamp": 2.359593152999878, "event": "ball missed"}, {"norm_timestamp": 2.3595943450927734, "event": "motor layout: 0"}, {"norm_timestamp": 2.376382350921631, "event": "ball bounce"}, {"norm_timestamp": 2.3885560035705566, "event": "ball bounce"}, {"norm_timestamp": 2.409752130508423, "event": "ball return"}, {"norm_timestamp": 2.4432859420776367, "event": "ball bounce"}, {"norm_timestamp": 2.451228141784668, "event": "ball bounce"}, {"norm_timestamp": 2.4767282009124756, "event": "ball return"}, {"norm_timestamp": 2.5103611946105957, "event": "ball bounce"}, {"norm_timestamp": 2.513993263244629, "event": "ball bounce"}, {"norm_timestamp": 2.5442240238189697, "event": "ball return"}, {"norm_timestamp": 2.5766141414642334, "event": "ball bounce"}, {"norm_timestamp": 2.5774972438812256, "event": "ball bounce"}, {"norm_timestamp": 2.6133360862731934, "event": "ball missed"}, {"norm_timestamp": 2.6133391857147217, "event": "motor layout: 0"}, {"norm_timestamp": 2.6300442218780518, "event": "ball bounce"}, {"norm_timestamp": 2.6343631744384766, "event": "ball bounce"}, {"norm_timestamp": 2.665865182876587, "event": "ball missed"}, {"norm_timestamp": 2.6658663749694824, "event": "motor layout: 0"}, {"norm_timestamp": 2.6828222274780273, "event": "ball bounce"}, {"norm_timestamp": 2.7163991928100586, "event": "ball return"}, {"norm_timestamp": 2.74236798286438, "event": "ball bounce"}, {"norm_timestamp": 2.749235153198242, "event": "ball bounce"}, {"norm_timestamp": 2.7827513217926025, "event": "ball return"}, {"norm_timestamp": 2.8168790340423584, "event": "ball bounce"}, {"norm_timestamp": 2.852735996246338, "event": "ball missed"}, {"norm_timestamp": 2.8527369499206543, "event": "motor layout: 0"}, {"norm_timestamp": 2.8695790767669678, "event": "ball bounce"}, {"norm_timestamp": 2.9058454036712646, "event": "ball missed"}, {"norm_timestamp": 2.905846118927002, "event": "motor layout: 0"}, {"norm_timestamp": 2.922497034072876, "event": "ball bounce"}, {"norm_timestamp": 2.9390311241149902, "event": "ball bounce"}, {"norm_timestamp": 2.9555461406707764, "event": "ball return"}, {"norm_timestamp": 2.9884321689605713, "event": "ball bounce"}, {"norm_timestamp": 3.0091712474823, "event": "ball bounce"}, {"norm_timestamp": 3.0215420722961426, "event": "ball return"}, {"norm_timestamp": 3.0546741485595703, "event": "ball bounce"}, {"norm_timestamp": 3.0797340869903564, "event": "ball bounce"}, {"norm_timestamp": 3.0875461101531982, "event": "ball return"}, {"norm_timestamp": 3.1208713054656982, "event": "ball bounce"}, {"norm_timestamp": 3.1506192684173584, "event": "ball bounce"}, {"norm_timestamp": 3.1541240215301514, "event": "ball return"}, {"norm_timestamp": 3.1875932216644287, "event": "ball bounce"}, {"norm_timestamp": 3.2201220989227295, "event": "ball return"}, {"norm_timestamp": 3.2209830284118652, "event": "ball bounce"}, {"norm_timestamp": 3.252930164337158, "event": "ball bounce"}, {"norm_timestamp": 3.2897682189941406, "event": "ball missed"}, {"norm_timestamp": 3.289769172668457, "event": "motor layout: 0"}, {"norm_timestamp": 3.3064181804656982, "event": "ball bounce"}, {"norm_timestamp": 3.34281325340271, "event": "ball missed"}, {"norm_timestamp": 3.3428142070770264, "event": "motor layout: 0"}, {"norm_timestamp": 3.359523057937622, "event": "ball bounce"}, {"norm_timestamp": 3.3719711303710938, "event": "ball bounce"}, {"norm_timestamp": 3.393097162246704, "event": "ball return"}, {"norm_timestamp": 3.4262630939483643, "event": "ball bounce"}, {"norm_timestamp": 3.434221029281616, "event": "ball bounce"}, {"norm_timestamp": 3.462430238723755, "event": "ball missed"}, {"norm_timestamp": 3.4624311923980713, "event": "motor layout: 0"}, {"norm_timestamp": 3.478952169418335, "event": "ball bounce"}, {"norm_timestamp": 3.5152029991149902, "event": "ball missed"}, {"norm_timestamp": 3.5152041912078857, "event": "motor layout: 0"}, {"norm_timestamp": 3.5320651531219482, "event": "ball bounce"}, {"norm_timestamp": 3.5682780742645264, "event": "ball missed"}, {"norm_timestamp": 3.5682790279388428, "event": "motor layout: 0"}, {"norm_timestamp": 3.5851283073425293, "event": "ball bounce"}, {"norm_timestamp": 3.5975332260131836, "event": "ball bounce"}, {"norm_timestamp": 3.6183412075042725, "event": "ball return"}, {"norm_timestamp": 3.651459217071533, "event": "ball bounce"}, {"norm_timestamp": 3.6595101356506348, "event": "ball bounce"}, {"norm_timestamp": 3.6878182888031006, "event": "ball missed"}, {"norm_timestamp": 3.687819004058838, "event": "motor layout: 0"}, {"norm_timestamp": 3.7047781944274902, "event": "ball bounce"}, {"norm_timestamp": 3.711925983428955, "event": "ball bounce"}, {"norm_timestamp": 3.7411460876464844, "event": "ball missed"}, {"norm_timestamp": 3.74114727973938, "event": "motor layout: 0"}, {"norm_timestamp": 3.7579729557037354, "event": "ball bounce"}, {"norm_timestamp": 3.7801461219787598, "event": "ball bounce"}, {"norm_timestamp": 3.7917981147766113, "event": "ball return"}, {"norm_timestamp": 3.825792074203491, "event": "ball bounce"}, {"norm_timestamp": 3.8622472286224365, "event": "ball missed"}, {"norm_timestamp": 3.862248182296753, "event": "motor layout: 0"}, {"norm_timestamp": 3.8789732456207275, "event": "ball bounce"}, {"norm_timestamp": 3.9121201038360596, "event": "ball return"}, {"norm_timestamp": 3.9453842639923096, "event": "ball bounce"}, {"norm_timestamp": 3.9787821769714355, "event": "ball return"}, {"norm_timestamp": 4.0121541023254395, "event": "ball bounce"}, {"norm_timestamp": 4.045232057571411, "event": "ball return"}, {"norm_timestamp": 4.078330039978027, "event": "ball bounce"}, {"norm_timestamp": 4.090658187866211, "event": "ball bounce"}, {"norm_timestamp": 4.111886024475098, "event": "ball return"}, {"norm_timestamp": 4.145158290863037, "event": "ball bounce"}, {"norm_timestamp": 4.178739309310913, "event": "ball return"}, {"norm_timestamp": 4.211826324462891, "event": "ball bounce"}, {"norm_timestamp": 4.245311260223389, "event": "ball return"}, {"norm_timestamp": 4.278635025024414, "event": "ball bounce"}, {"norm_timestamp": 4.315417051315308, "event": "ball missed"}, {"norm_timestamp": 4.315418243408203, "event": "motor layout: 0"}, {"norm_timestamp": 4.3320231437683105, "event": "ball bounce"}, {"norm_timestamp": 4.368285179138184, "event": "ball missed"}, {"norm_timestamp": 4.3682861328125, "event": "motor layout: 0"}, {"norm_timestamp": 4.38512921333313, "event": "ball bounce"}, {"norm_timestamp": 4.397488117218018, "event": "ball bounce"}, {"norm_timestamp": 4.418692111968994, "event": "ball return"}, {"norm_timestamp": 4.452554941177368, "event": "ball bounce"}, {"norm_timestamp": 4.460485219955444, "event": "ball bounce"}, {"norm_timestamp": 4.4890360832214355, "event": "ball missed"}, {"norm_timestamp": 4.489037036895752, "event": "motor layout: 0"}, {"norm_timestamp": 4.506126165390015, "event": "ball bounce"}, {"norm_timestamp": 4.539653062820435, "event": "ball return"}, {"norm_timestamp": 4.547561168670654, "event": "ball bounce"}, {"norm_timestamp": 4.5731201171875, "event": "ball bounce"}, {"norm_timestamp": 4.609208106994629, "event": "ball missed"}, {"norm_timestamp": 4.609209060668945, "event": "motor layout: 0"}, {"norm_timestamp": 4.609210252761841, "event": "ball return"}, {"norm_timestamp": 4.626150131225586, "event": "ball bounce"}, {"norm_timestamp": 4.63512110710144, "event": "ball bounce"}, {"norm_timestamp": 4.659793138504028, "event": "ball return"}, {"norm_timestamp": 4.6905951499938965, "event": "ball bounce"}, {"norm_timestamp": 4.693238973617554, "event": "ball bounce"}, {"norm_timestamp": 4.726464033126831, "event": "ball return"}, {"norm_timestamp": 4.745957136154175, "event": "ball bounce"}, {"norm_timestamp": 4.760069131851196, "event": "ball bounce"}, {"norm_timestamp": 4.796597957611084, "event": "ball missed"}, {"norm_timestamp": 4.7965991497039795, "event": "motor layout: 0"}, {"norm_timestamp": 4.813561201095581, "event": "ball bounce"}, {"norm_timestamp": 4.847086191177368, "event": "ball return"}, {"norm_timestamp": 4.880191326141357, "event": "ball bounce"}, {"norm_timestamp": 4.91168212890625, "event": "ball bounce"}, {"norm_timestamp": 4.913453102111816, "event": "ball return"}, {"norm_timestamp": 4.948501110076904, "event": "ball bounce"}, {"norm_timestamp": 4.983749151229858, "event": "ball return"}, {"norm_timestamp": 5.017487049102783, "event": "ball bounce"}, {"norm_timestamp": 5.051346302032471, "event": "ball return"}, {"norm_timestamp": 5.084779977798462, "event": "ball bounce"}, {"norm_timestamp": 5.120187282562256, "event": "ball missed"}, {"norm_timestamp": 5.120188236236572, "event": "motor layout: 0"}, {"norm_timestamp": 5.137228012084961, "event": "ball bounce"}, {"norm_timestamp": 5.170469045639038, "event": "ball return"}, {"norm_timestamp": 5.2036731243133545, "event": "ball bounce"}, {"norm_timestamp": 5.237202167510986, "event": "ball return"}, {"norm_timestamp": 5.270602226257324, "event": "ball bounce"}, {"norm_timestamp": 5.307234048843384, "event": "ball return"}, {"norm_timestamp": 5.344223260879517, "event": "ball bounce"}, {"norm_timestamp": 5.35741114616394, "event": "ball bounce"}, {"norm_timestamp": 5.380043029785156, "event": "ball return"}, {"norm_timestamp": 5.414698362350464, "event": "ball bounce"}, {"norm_timestamp": 5.450281143188477, "event": "ball return"}, {"norm_timestamp": 5.486804246902466, "event": "ball bounce"}, {"norm_timestamp": 5.522372245788574, "event": "ball return"}, {"norm_timestamp": 5.5584540367126465, "event": "ball bounce"}, {"norm_timestamp": 5.598282337188721, "event": "ball missed"}, {"norm_timestamp": 5.598283052444458, "event": "motor layout: 0"}, {"norm_timestamp": 5.617577314376831, "event": "ball bounce"}, {"norm_timestamp": 5.635501146316528, "event": "ball bounce"}, {"norm_timestamp": 5.652874946594238, "event": "ball return"}, {"norm_timestamp": 5.6860082149505615, "event": "ball bounce"}, {"norm_timestamp": 5.706858396530151, "event": "ball bounce"}, {"norm_timestamp": 5.720168113708496, "event": "ball return"}, {"norm_timestamp": 5.754591226577759, "event": "ball bounce"}, {"norm_timestamp": 5.7785022258758545, "event": "ball bounce"}, {"norm_timestamp": 5.7883100509643555, "event": "ball return"}, {"norm_timestamp": 5.821786165237427, "event": "ball bounce"}, {"norm_timestamp": 5.850084066390991, "event": "ball bounce"}, {"norm_timestamp": 5.858004331588745, "event": "ball missed"}, {"norm_timestamp": 5.858005046844482, "event": "motor layout: 0"}, {"norm_timestamp": 5.874959230422974, "event": "ball bounce"}, {"norm_timestamp": 5.896855115890503, "event": "ball bounce"}, {"norm_timestamp": 5.908578157424927, "event": "ball return"}, {"norm_timestamp": 5.942622184753418, "event": "ball bounce"}, {"norm_timestamp": 5.978819131851196, "event": "ball missed"}, {"norm_timestamp": 5.978820085525513, "event": "motor layout: 0"}, {"norm_timestamp": 5.995743274688721, "event": "ball bounce"}, {"norm_timestamp": 6.031508922576904, "event": "ball return"}, {"norm_timestamp": 6.0666821002960205, "event": "ball bounce"}, {"norm_timestamp": 6.102710008621216, "event": "ball missed"}, {"norm_timestamp": 6.102710962295532, "event": "motor layout: 0"}, {"norm_timestamp": 6.119668245315552, "event": "ball bounce"}, {"norm_timestamp": 6.153471231460571, "event": "ball return"}, {"norm_timestamp": 6.185800313949585, "event": "ball bounce"}, {"norm_timestamp": 6.217608213424683, "event": "ball bounce"}, {"norm_timestamp": 6.219320058822632, "event": "ball return"}, {"norm_timestamp": 6.252002000808716, "event": "ball bounce"}, {"norm_timestamp": 6.284570217132568, "event": "ball return"}, {"norm_timestamp": 6.318266153335571, "event": "ball bounce"}, {"norm_timestamp": 6.3531739711761475, "event": "ball missed"}, {"norm_timestamp": 6.353175163269043, "event": "motor layout: 0"}, {"norm_timestamp": 6.369616270065308, "event": "ball bounce"}, {"norm_timestamp": 6.402213096618652, "event": "ball return"}, {"norm_timestamp": 6.427661180496216, "event": "ball bounce"}, {"norm_timestamp": 6.435284376144409, "event": "ball bounce"}, {"norm_timestamp": 6.468080282211304, "event": "ball return"}, {"norm_timestamp": 6.500251293182373, "event": "ball bounce"}, {"norm_timestamp": 6.53266716003418, "event": "ball return"}, {"norm_timestamp": 6.565360069274902, "event": "ball bounce"}, {"norm_timestamp": 6.58917498588562, "event": "ball bounce"}, {"norm_timestamp": 6.6000871658325195, "event": "ball missed"}, {"norm_timestamp": 6.600088119506836, "event": "motor layout: 0"}, {"norm_timestamp": 6.6161651611328125, "event": "ball bounce"}, {"norm_timestamp": 6.648798227310181, "event": "ball return"}, {"norm_timestamp": 6.68124532699585, "event": "ball bounce"}, {"norm_timestamp": 6.713824987411499, "event": "ball return"}, {"norm_timestamp": 6.745659112930298, "event": "ball bounce"}, {"norm_timestamp": 6.778156995773315, "event": "ball return"}, {"norm_timestamp": 6.810973167419434, "event": "ball bounce"}, {"norm_timestamp": 6.843991041183472, "event": "ball return"}, {"norm_timestamp": 6.876051187515259, "event": "ball bounce"}, {"norm_timestamp": 6.9082841873168945, "event": "ball return"}, {"norm_timestamp": 6.940992116928101, "event": "ball bounce"}, {"norm_timestamp": 6.973681211471558, "event": "ball return"}, {"norm_timestamp": 7.006014347076416, "event": "ball bounce"}, {"norm_timestamp": 7.03852105140686, "event": "ball return"}, {"norm_timestamp": 7.071451187133789, "event": "ball bounce"}, {"norm_timestamp": 7.107813119888306, "event": "ball return"}, {"norm_timestamp": 7.1474690437316895, "event": "ball bounce"}, {"norm_timestamp": 7.185197114944458, "event": "ball return"}, {"norm_timestamp": 7.219842195510864, "event": "ball bounce"}, {"norm_timestamp": 7.252655029296875, "event": "ball return"}, {"norm_timestamp": 7.2859110832214355, "event": "ball bounce"}, {"norm_timestamp": 7.32190203666687, "event": "ball missed"}, {"norm_timestamp": 7.321903228759766, "event": "motor layout: 0"}, {"norm_timestamp": 7.338074207305908, "event": "ball bounce"}, {"norm_timestamp": 7.3708860874176025, "event": "ball return"}, {"norm_timestamp": 7.403250217437744, "event": "ball bounce"}, {"norm_timestamp": 7.435866117477417, "event": "ball return"}, {"norm_timestamp": 7.468071222305298, "event": "ball bounce"}, {"norm_timestamp": 7.500248193740845, "event": "ball return"}, {"norm_timestamp": 7.532700300216675, "event": "ball bounce"}, {"norm_timestamp": 7.54478907585144, "event": "ball bounce"}, {"norm_timestamp": 7.56531023979187, "event": "ball return"}, {"norm_timestamp": 7.598112106323242, "event": "ball bounce"}, {"norm_timestamp": 7.630895137786865, "event": "ball return"}, {"norm_timestamp": 7.663698196411133, "event": "ball bounce"}, {"norm_timestamp": 7.696087121963501, "event": "ball return"}, {"norm_timestamp": 7.72855806350708, "event": "ball bounce"}, {"norm_timestamp": 7.763379335403442, "event": "ball missed"}, {"norm_timestamp": 7.763380289077759, "event": "motor layout: 0"}, {"norm_timestamp": 7.779322147369385, "event": "ball bounce"}, {"norm_timestamp": 7.8011980056762695, "event": "ball bounce"}, {"norm_timestamp": 7.812547206878662, "event": "ball return"}, {"norm_timestamp": 7.845720052719116, "event": "ball bounce"}, {"norm_timestamp": 7.880939960479736, "event": "ball missed"}, {"norm_timestamp": 7.880941152572632, "event": "motor layout: 0"}, {"norm_timestamp": 7.897510290145874, "event": "ball bounce"}, {"norm_timestamp": 7.932923078536987, "event": "ball missed"}, {"norm_timestamp": 7.932924270629883, "event": "motor layout: 0"}, {"norm_timestamp": 7.949231147766113, "event": "ball bounce"}, {"norm_timestamp": 7.95604395866394, "event": "ball bounce"}, {"norm_timestamp": 7.981703281402588, "event": "ball return"}, {"norm_timestamp": 8.005575180053711, "event": "ball bounce"}, {"norm_timestamp": 8.014066219329834, "event": "ball bounce"}, {"norm_timestamp": 8.04624629020691, "event": "ball return"}, {"norm_timestamp": 8.054843187332153, "event": "ball bounce"}, {"norm_timestamp": 8.07858920097351, "event": "ball bounce"}, {"norm_timestamp": 8.104016065597534, "event": "ball bounce"}, {"norm_timestamp": 8.113440036773682, "event": "ball missed"}, {"norm_timestamp": 8.113440990447998, "event": "motor layout: 0"}, {"norm_timestamp": 8.129768133163452, "event": "ball bounce"}, {"norm_timestamp": 8.162122964859009, "event": "ball return"}, {"norm_timestamp": 8.194854259490967, "event": "ball bounce"}, {"norm_timestamp": 8.22732424736023, "event": "ball return"}, {"norm_timestamp": 8.259489059448242, "event": "ball bounce"}, {"norm_timestamp": 8.29234504699707, "event": "ball return"}, {"norm_timestamp": 8.325706958770752, "event": "ball bounce"}, {"norm_timestamp": 8.337516069412231, "event": "ball bounce"}, {"norm_timestamp": 8.358022212982178, "event": "ball return"}, {"norm_timestamp": 8.390555143356323, "event": "ball bounce"}, {"norm_timestamp": 8.423316955566406, "event": "ball return"}, {"norm_timestamp": 8.455586194992065, "event": "ball bounce"}, {"norm_timestamp": 8.488022089004517, "event": "ball return"}, {"norm_timestamp": 8.52022409439087, "event": "ball bounce"}, {"norm_timestamp": 8.553672313690186, "event": "ball return"}, {"norm_timestamp": 8.586814165115356, "event": "ball bounce"}, {"norm_timestamp": 8.621927261352539, "event": "ball missed"}, {"norm_timestamp": 8.621928215026855, "event": "motor layout: 0"}, {"norm_timestamp": 8.63836121559143, "event": "ball bounce"}, {"norm_timestamp": 8.67101526260376, "event": "ball return"}, {"norm_timestamp": 8.678783178329468, "event": "ball bounce"}, {"norm_timestamp": 8.70353102684021, "event": "ball bounce"}, {"norm_timestamp": 8.738521099090576, "event": "ball missed"}, {"norm_timestamp": 8.738522052764893, "event": "motor layout: 0"}, {"norm_timestamp": 8.754813194274902, "event": "ball bounce"}, {"norm_timestamp": 8.759093999862671, "event": "ball bounce"}, {"norm_timestamp": 8.789977073669434, "event": "ball missed"}, {"norm_timestamp": 8.789978265762329, "event": "motor layout: 0"}, {"norm_timestamp": 8.806319236755371, "event": "ball bounce"}, {"norm_timestamp": 8.839116096496582, "event": "ball return"}, {"norm_timestamp": 8.864784240722656, "event": "ball bounce"}, {"norm_timestamp": 8.871687173843384, "event": "ball bounce"}, {"norm_timestamp": 8.90406608581543, "event": "ball return"}, {"norm_timestamp": 8.936675071716309, "event": "ball bounce"}, {"norm_timestamp": 8.971446990966797, "event": "ball missed"}, {"norm_timestamp": 8.971446990966797, "event": "motor layout: 0"}, {"norm_timestamp": 8.987874031066895, "event": "ball bounce"}, {"norm_timestamp": 9.020312070846558, "event": "ball return"}, {"norm_timestamp": 9.028082132339478, "event": "ball bounce"}, {"norm_timestamp": 9.052454233169556, "event": "ball bounce"}, {"norm_timestamp": 9.08711314201355, "event": "ball missed"}, {"norm_timestamp": 9.087114334106445, "event": "motor layout: 0"}, {"norm_timestamp": 9.103387117385864, "event": "ball bounce"}, {"norm_timestamp": 9.132006168365479, "event": "ball bounce"}, {"norm_timestamp": 9.13538932800293, "event": "ball return"}, {"norm_timestamp": 9.167433261871338, "event": "ball bounce"}, {"norm_timestamp": 9.202580213546753, "event": "ball missed"}, {"norm_timestamp": 9.20258092880249, "event": "motor layout: 0"}, {"norm_timestamp": 9.21887993812561, "event": "ball bounce"}, {"norm_timestamp": 9.25253701210022, "event": "ball return"}, {"norm_timestamp": 9.285774230957031, "event": "ball bounce"}, {"norm_timestamp": 9.3180673122406, "event": "ball return"}, {"norm_timestamp": 9.350816011428833, "event": "ball bounce"}, {"norm_timestamp": 9.38295316696167, "event": "ball return"}, {"norm_timestamp": 9.415115118026733, "event": "ball bounce"}, {"norm_timestamp": 9.449785232543945, "event": "ball missed"}, {"norm_timestamp": 9.449785232543945, "event": "motor layout: 0"}, {"norm_timestamp": 9.466018199920654, "event": "ball bounce"}, {"norm_timestamp": 9.494937181472778, "event": "ball bounce"}, {"norm_timestamp": 9.50007438659668, "event": "ball return"}, {"norm_timestamp": 9.534459114074707, "event": "ball bounce"}, {"norm_timestamp": 9.56935429573059, "event": "ball missed"}, {"norm_timestamp": 9.569355010986328, "event": "motor layout: 0"}, {"norm_timestamp": 9.585917234420776, "event": "ball bounce"}, {"norm_timestamp": 9.590111255645752, "event": "ball bounce"}, {"norm_timestamp": 9.618182182312012, "event": "ball return"}, {"norm_timestamp": 9.634010076522827, "event": "ball bounce"}, {"norm_timestamp": 9.650461196899414, "event": "ball bounce"}, {"norm_timestamp": 9.67871618270874, "event": "ball bounce"}, {"norm_timestamp": 9.683007955551147, "event": "ball return"}, {"norm_timestamp": 9.714977025985718, "event": "ball bounce"}, {"norm_timestamp": 9.722531080245972, "event": "ball bounce"}, {"norm_timestamp": 9.747538328170776, "event": "ball return"}, {"norm_timestamp": 9.767088174819946, "event": "ball bounce"}, {"norm_timestamp": 9.77981424331665, "event": "ball bounce"}, {"norm_timestamp": 9.811508178710938, "event": "ball bounce"}, {"norm_timestamp": 9.814075231552124, "event": "ball return"}, {"norm_timestamp": 9.848961114883423, "event": "ball bounce"}, {"norm_timestamp": 9.856673002243042, "event": "ball bounce"}, {"norm_timestamp": 9.881473064422607, "event": "ball return"}, {"norm_timestamp": 9.901123046875, "event": "ball bounce"}, {"norm_timestamp": 9.914505243301392, "event": "ball bounce"}, {"norm_timestamp": 9.946617126464844, "event": "ball bounce"}, {"norm_timestamp": 9.949961185455322, "event": "ball missed"}, {"norm_timestamp": 9.949962377548218, "event": "motor layout: 0"}, {"norm_timestamp": 9.966265201568604, "event": "ball bounce"}, {"norm_timestamp": 9.998685121536255, "event": "ball return"}, {"norm_timestamp": 10.006405115127563, "event": "ball bounce"}, {"norm_timestamp": 10.031350135803223, "event": "ball bounce"}, {"norm_timestamp": 10.0640230178833, "event": "ball return"}, {"norm_timestamp": 10.096622228622437, "event": "ball bounce"}, {"norm_timestamp": 10.128014087677002, "event": "ball bounce"}, {"norm_timestamp": 10.131371974945068, "event": "ball missed"}, {"norm_timestamp": 10.131373167037964, "event": "motor layout: 0"}, {"norm_timestamp": 10.131373167037964, "event": "ball return"}, {"norm_timestamp": 10.147882223129272, "event": "ball bounce"}, {"norm_timestamp": 10.15459132194519, "event": "ball bounce"}, {"norm_timestamp": 10.180118083953857, "event": "ball return"}, {"norm_timestamp": 10.204142093658447, "event": "ball bounce"}, {"norm_timestamp": 10.212447166442871, "event": "ball bounce"}, {"norm_timestamp": 10.244819164276123, "event": "ball return"}, {"norm_timestamp": 10.25320315361023, "event": "ball bounce"}, {"norm_timestamp": 10.277144193649292, "event": "ball bounce"}, {"norm_timestamp": 10.303276062011719, "event": "ball bounce"}, {"norm_timestamp": 10.310136079788208, "event": "ball return"}, {"norm_timestamp": 10.343076229095459, "event": "ball bounce"}, {"norm_timestamp": 10.35338020324707, "event": "ball bounce"}, {"norm_timestamp": 10.375700235366821, "event": "ball return"}, {"norm_timestamp": 10.402873039245605, "event": "ball bounce"}, {"norm_timestamp": 10.408128023147583, "event": "ball bounce"}, {"norm_timestamp": 10.44031834602356, "event": "ball return"}, {"norm_timestamp": 10.452345132827759, "event": "ball bounce"}, {"norm_timestamp": 10.472933053970337, "event": "ball bounce"}, {"norm_timestamp": 10.501699209213257, "event": "ball bounce"}, {"norm_timestamp": 10.506850004196167, "event": "ball return"}, {"norm_timestamp": 10.541190147399902, "event": "ball bounce"}, {"norm_timestamp": 10.551520109176636, "event": "ball bounce"}, {"norm_timestamp": 10.573880195617676, "event": "ball return"}, {"norm_timestamp": 10.600947141647339, "event": "ball bounce"}, {"norm_timestamp": 10.606001138687134, "event": "ball bounce"}, {"norm_timestamp": 10.638782262802124, "event": "ball return"}, {"norm_timestamp": 10.650572061538696, "event": "ball bounce"}, {"norm_timestamp": 10.67065715789795, "event": "ball bounce"}, {"norm_timestamp": 10.699687242507935, "event": "ball bounce"}, {"norm_timestamp": 10.704008340835571, "event": "ball return"}, {"norm_timestamp": 10.73784327507019, "event": "ball bounce"}, {"norm_timestamp": 10.749809265136719, "event": "ball bounce"}, {"norm_timestamp": 10.770333290100098, "event": "ball return"}, {"norm_timestamp": 10.799336194992065, "event": "ball bounce"}, {"norm_timestamp": 10.80307912826538, "event": "ball bounce"}, {"norm_timestamp": 10.836027145385742, "event": "ball return"}, {"norm_timestamp": 10.84975004196167, "event": "ball bounce"}, {"norm_timestamp": 10.868726015090942, "event": "ball bounce"}, {"norm_timestamp": 10.899539232254028, "event": "ball bounce"}, {"norm_timestamp": 10.902960062026978, "event": "ball return"}, {"norm_timestamp": 10.937191247940063, "event": "ball bounce"}, {"norm_timestamp": 10.949209213256836, "event": "ball bounce"}, {"norm_timestamp": 10.969709157943726, "event": "ball return"}, {"norm_timestamp": 10.998474359512329, "event": "ball bounce"}, {"norm_timestamp": 11.001978158950806, "event": "ball bounce"}, {"norm_timestamp": 11.034650087356567, "event": "ball return"}, {"norm_timestamp": 11.048160076141357, "event": "ball bounce"}, {"norm_timestamp": 11.06704831123352, "event": "ball bounce"}, {"norm_timestamp": 11.097508192062378, "event": "ball bounce"}, {"norm_timestamp": 11.10169005393982, "event": "ball missed"}, {"norm_timestamp": 11.101691246032715, "event": "motor layout: 0"}, {"norm_timestamp": 11.117969274520874, "event": "ball bounce"}, {"norm_timestamp": 11.14700722694397, "event": "ball bounce"}, {"norm_timestamp": 11.150415182113647, "event": "ball return"}, {"norm_timestamp": 11.182882070541382, "event": "ball bounce"}, {"norm_timestamp": 11.21569037437439, "event": "ball return"}, {"norm_timestamp": 11.244689226150513, "event": "ball bounce"}, {"norm_timestamp": 11.24812912940979, "event": "ball bounce"}, {"norm_timestamp": 11.28057312965393, "event": "ball return"}, {"norm_timestamp": 11.31360936164856, "event": "ball bounce"}, {"norm_timestamp": 11.343537092208862, "event": "ball bounce"}, {"norm_timestamp": 11.346999168395996, "event": "ball return"}, {"norm_timestamp": 11.379731178283691, "event": "ball bounce"}, {"norm_timestamp": 11.412134170532227, "event": "ball return"}, {"norm_timestamp": 11.441001176834106, "event": "ball bounce"}, {"norm_timestamp": 11.444328308105469, "event": "ball bounce"}, {"norm_timestamp": 11.476621150970459, "event": "ball return"}, {"norm_timestamp": 11.509090185165405, "event": "ball bounce"}, {"norm_timestamp": 11.53798222541809, "event": "ball bounce"}, {"norm_timestamp": 11.541392087936401, "event": "ball return"}, {"norm_timestamp": 11.574087142944336, "event": "ball bounce"}, {"norm_timestamp": 11.609779357910156, "event": "ball missed"}, {"norm_timestamp": 11.609780311584473, "event": "motor layout: 0"}, {"norm_timestamp": 11.626140117645264, "event": "ball bounce"}, {"norm_timestamp": 11.63308310508728, "event": "ball bounce"}, {"norm_timestamp": 11.661593198776245, "event": "ball missed"}, {"norm_timestamp": 11.661594152450562, "event": "motor layout: 0"}, {"norm_timestamp": 11.682106256484985, "event": "ball bounce"}, {"norm_timestamp": 11.713293075561523, "event": "ball bounce"}, {"norm_timestamp": 11.716998100280762, "event": "ball return"}, {"norm_timestamp": 11.75015115737915, "event": "ball bounce"}, {"norm_timestamp": 11.787628173828125, "event": "ball missed"}, {"norm_timestamp": 11.787629127502441, "event": "motor layout: 0"}, {"norm_timestamp": 11.804208278656006, "event": "ball bounce"}, {"norm_timestamp": 11.826028108596802, "event": "ball bounce"}, {"norm_timestamp": 11.837651252746582, "event": "ball return"}, {"norm_timestamp": 11.870577096939087, "event": "ball bounce"}, {"norm_timestamp": 11.905953168869019, "event": "ball missed"}, {"norm_timestamp": 11.905954122543335, "event": "motor layout: 0"}, {"norm_timestamp": 11.922307014465332, "event": "ball bounce"}, {"norm_timestamp": 11.957550048828125, "event": "ball missed"}, {"norm_timestamp": 11.957550048828125, "event": "motor layout: 0"}, {"norm_timestamp": 11.973857164382935, "event": "ball bounce"}, {"norm_timestamp": 12.00913405418396, "event": "ball missed"}, {"norm_timestamp": 12.009135246276855, "event": "motor layout: 0"}, {"norm_timestamp": 12.025520086288452, "event": "ball bounce"}, {"norm_timestamp": 12.037568092346191, "event": "ball bounce"}, {"norm_timestamp": 12.058083057403564, "event": "ball return"}, {"norm_timestamp": 12.090596199035645, "event": "ball bounce"}, {"norm_timestamp": 12.098315000534058, "event": "ball bounce"}, {"norm_timestamp": 12.123112201690674, "event": "ball return"}, {"norm_timestamp": 12.15544605255127, "event": "ball bounce"}, {"norm_timestamp": 12.158851146697998, "event": "ball bounce"}, {"norm_timestamp": 12.187098264694214, "event": "ball return"}, {"norm_timestamp": 12.21841311454773, "event": "ball bounce"}, {"norm_timestamp": 12.219251155853271, "event": "ball bounce"}, {"norm_timestamp": 12.251781225204468, "event": "ball return"}, {"norm_timestamp": 12.279201030731201, "event": "ball bounce"}, {"norm_timestamp": 12.284322023391724, "event": "ball bounce"}, {"norm_timestamp": 12.31704330444336, "event": "ball return"}, {"norm_timestamp": 12.340558052062988, "event": "ball bounce"}, {"norm_timestamp": 12.35006833076477, "event": "ball bounce"}, {"norm_timestamp": 12.382383108139038, "event": "ball return"}, {"norm_timestamp": 12.401226282119751, "event": "ball bounce"}, {"norm_timestamp": 12.414935111999512, "event": "ball bounce"}, {"norm_timestamp": 12.449405193328857, "event": "ball missed"}, {"norm_timestamp": 12.449406147003174, "event": "motor layout: 0"}, {"norm_timestamp": 12.465738296508789, "event": "ball bounce"}, {"norm_timestamp": 12.49822735786438, "event": "ball return"}, {"norm_timestamp": 12.530855178833008, "event": "ball bounce"}, {"norm_timestamp": 12.563461065292358, "event": "ball return"}, {"norm_timestamp": 12.595903158187866, "event": "ball bounce"}, {"norm_timestamp": 12.62844729423523, "event": "ball return"}, {"norm_timestamp": 12.660969257354736, "event": "ball bounce"}, {"norm_timestamp": 12.69362211227417, "event": "ball return"}, {"norm_timestamp": 12.707022190093994, "event": "ball bounce"}, {"norm_timestamp": 12.725677013397217, "event": "ball bounce"}, {"norm_timestamp": 12.758366346359253, "event": "ball return"}, {"norm_timestamp": 12.790939092636108, "event": "ball bounce"}, {"norm_timestamp": 12.823836088180542, "event": "ball return"}, {"norm_timestamp": 12.857093095779419, "event": "ball bounce"}, {"norm_timestamp": 12.889581203460693, "event": "ball return"}, {"norm_timestamp": 12.922235250473022, "event": "ball bounce"}, {"norm_timestamp": 12.954437255859375, "event": "ball return"}, {"norm_timestamp": 12.986946105957031, "event": "ball bounce"}, {"norm_timestamp": 13.019343137741089, "event": "ball return"}, {"norm_timestamp": 13.052038192749023, "event": "ball bounce"}, {"norm_timestamp": 13.084481000900269, "event": "ball return"}, {"norm_timestamp": 13.116453170776367, "event": "ball bounce"}, {"norm_timestamp": 13.148434162139893, "event": "ball return"}, {"norm_timestamp": 13.180427074432373, "event": "ball bounce"}, {"norm_timestamp": 13.187065124511719, "event": "ball bounce"}, {"norm_timestamp": 13.213517189025879, "event": "ball return"}, {"norm_timestamp": 13.247541189193726, "event": "ball bounce"}, {"norm_timestamp": 13.280270099639893, "event": "ball return"}, {"norm_timestamp": 13.313561201095581, "event": "ball bounce"}, {"norm_timestamp": 13.346582174301147, "event": "ball return"}, {"norm_timestamp": 13.378892183303833, "event": "ball bounce"}, {"norm_timestamp": 13.413800239562988, "event": "ball missed"}, {"norm_timestamp": 13.413800239562988, "event": "motor layout: 0"}, {"norm_timestamp": 13.430092096328735, "event": "ball bounce"}, {"norm_timestamp": 13.44205904006958, "event": "ball bounce"}, {"norm_timestamp": 13.462156057357788, "event": "ball return"}, {"norm_timestamp": 13.493986129760742, "event": "ball bounce"}, {"norm_timestamp": 13.501538038253784, "event": "ball bounce"}, {"norm_timestamp": 13.526319026947021, "event": "ball return"}, {"norm_timestamp": 13.558659076690674, "event": "ball bounce"}, {"norm_timestamp": 13.562043190002441, "event": "ball bounce"}, {"norm_timestamp": 13.590805053710938, "event": "ball return"}, {"norm_timestamp": 13.622565269470215, "event": "ball bounce"}, {"norm_timestamp": 13.623423337936401, "event": "ball bounce"}, {"norm_timestamp": 13.655860185623169, "event": "ball return"}, {"norm_timestamp": 13.683397054672241, "event": "ball bounce"}, {"norm_timestamp": 13.688446283340454, "event": "ball bounce"}, {"norm_timestamp": 13.721045970916748, "event": "ball return"}, {"norm_timestamp": 13.744217157363892, "event": "ball bounce"}, {"norm_timestamp": 13.75340223312378, "event": "ball bounce"}, {"norm_timestamp": 13.785645008087158, "event": "ball return"}, {"norm_timestamp": 13.80431318283081, "event": "ball bounce"}, {"norm_timestamp": 13.818329095840454, "event": "ball bounce"}, {"norm_timestamp": 13.854586124420166, "event": "ball missed"}, {"norm_timestamp": 13.854587078094482, "event": "motor layout: 0"}, {"norm_timestamp": 13.871350049972534, "event": "ball bounce"}, {"norm_timestamp": 13.904039144515991, "event": "ball return"}, {"norm_timestamp": 13.936260223388672, "event": "ball bounce"}, {"norm_timestamp": 13.967166185379028, "event": "ball bounce"}, {"norm_timestamp": 13.968900203704834, "event": "ball return"}, {"norm_timestamp": 14.001329183578491, "event": "ball bounce"}, {"norm_timestamp": 14.033601999282837, "event": "ball return"}, {"norm_timestamp": 14.066180229187012, "event": "ball bounce"}, {"norm_timestamp": 14.09867811203003, "event": "ball return"}, {"norm_timestamp": 14.130374193191528, "event": "ball bounce"}, {"norm_timestamp": 14.164342164993286, "event": "ball return"}, {"norm_timestamp": 14.198357105255127, "event": "ball bounce"}, {"norm_timestamp": 14.207030057907104, "event": "ball bounce"}, {"norm_timestamp": 14.230785131454468, "event": "ball return"}, {"norm_timestamp": 14.263275146484375, "event": "ball bounce"}, {"norm_timestamp": 14.29581618309021, "event": "ball return"}, {"norm_timestamp": 14.328634262084961, "event": "ball bounce"}, {"norm_timestamp": 14.361632108688354, "event": "ball return"}, {"norm_timestamp": 14.394169092178345, "event": "ball bounce"}, {"norm_timestamp": 14.426812171936035, "event": "ball return"}, {"norm_timestamp": 14.449235200881958, "event": "ball bounce"}, {"norm_timestamp": 14.459474325180054, "event": "ball bounce"}, {"norm_timestamp": 14.49189019203186, "event": "ball return"}, {"norm_timestamp": 14.52438497543335, "event": "ball bounce"}, {"norm_timestamp": 14.559277057647705, "event": "ball missed"}, {"norm_timestamp": 14.559278011322021, "event": "motor layout: 0"}, {"norm_timestamp": 14.575522184371948, "event": "ball bounce"}, {"norm_timestamp": 14.59165906906128, "event": "ball bounce"}, {"norm_timestamp": 14.6078462600708, "event": "ball return"}, {"norm_timestamp": 14.640462160110474, "event": "ball bounce"}, {"norm_timestamp": 14.66096305847168, "event": "ball bounce"}, {"norm_timestamp": 14.673846960067749, "event": "ball return"}, {"norm_timestamp": 14.706914186477661, "event": "ball bounce"}, {"norm_timestamp": 14.729426145553589, "event": "ball bounce"}, {"norm_timestamp": 14.738763093948364, "event": "ball return"}, {"norm_timestamp": 14.770868301391602, "event": "ball bounce"}, {"norm_timestamp": 14.798139095306396, "event": "ball bounce"}, {"norm_timestamp": 14.805841207504272, "event": "ball missed"}, {"norm_timestamp": 14.805842161178589, "event": "motor layout: 0"}, {"norm_timestamp": 14.805843353271484, "event": "ball return"}, {"norm_timestamp": 14.822794198989868, "event": "ball bounce"}, {"norm_timestamp": 14.858494281768799, "event": "ball missed"}, {"norm_timestamp": 14.858495950698853, "event": "motor layout: 0"}]