[{"config": {"player": {"type": "DQN8-onlypos", "num_inputs": 5, "num_actions": 2, "seed": 20}, "fps": 100, "simulation_only": true, "num_episodes": 70, "paddle_size": [40, 250], "ball_size": 40, "ball_speed": 1, "screen_size": [600, 600], "start_time": 1688752815.870645, "reward": "1 if collided else -1 if done else 0"}}, {"norm_timestamp": 0.0, "event": "game begin"}, {"norm_timestamp": 0.025825023651123047, "event": "ball bounce"}, {"norm_timestamp": 0.0557398796081543, "event": "ball bounce"}, {"norm_timestamp": 0.0714728832244873, "event": "ball return"}, {"norm_timestamp": 0.117218017578125, "event": "ball bounce"}, {"norm_timestamp": 0.1645519733428955, "event": "ball missed"}, {"norm_timestamp": 0.16455292701721191, "event": "motor layout: 0"}, {"norm_timestamp": 0.18624496459960938, "event": "ball bounce"}, {"norm_timestamp": 0.19228482246398926, "event": "ball bounce"}, {"norm_timestamp": 0.23376893997192383, "event": "ball missed"}, {"norm_timestamp": 0.23376989364624023, "event": "motor layout: 0"}, {"norm_timestamp": 0.25558900833129883, "event": "ball bounce"}, {"norm_timestamp": 0.29861974716186523, "event": "ball return"}, {"norm_timestamp": 0.34210896492004395, "event": "ball bounce"}, {"norm_timestamp": 0.38777899742126465, "event": "ball return"}, {"norm_timestamp": 0.43346595764160156, "event": "ball bounce"}, {"norm_timestamp": 0.47960901260375977, "event": "ball missed"}, {"norm_timestamp": 0.47960996627807617, "event": "motor layout: 0"}, {"norm_timestamp": 0.5018911361694336, "event": "ball bounce"}, {"norm_timestamp": 0.5326089859008789, "event": "ball bounce"}, {"norm_timestamp": 0.5479857921600342, "event": "ball return"}, {"norm_timestamp": 0.5920979976654053, "event": "ball bounce"}, {"norm_timestamp": 0.6391921043395996, "event": "ball missed"}, {"norm_timestamp": 0.639193058013916, "event": "motor layout: 0"}, {"norm_timestamp": 0.660808801651001, "event": "ball bounce"}, {"norm_timestamp": 0.6698980331420898, "event": "ball bounce"}, {"norm_timestamp": 0.7038710117340088, "event": "ball return"}, {"norm_timestamp": 0.7354118824005127, "event": "ball bounce"}, {"norm_timestamp": 0.7467241287231445, "event": "ball bounce"}, {"norm_timestamp": 0.7897639274597168, "event": "ball return"}, {"norm_timestamp": 0.8010358810424805, "event": "ball bounce"}, {"norm_timestamp": 0.8327138423919678, "event": "ball bounce"}, {"norm_timestamp": 0.8665859699249268, "event": "ball bounce"}, {"norm_timestamp": 0.8791847229003906, "event": "ball missed"}, {"norm_timestamp": 0.8791859149932861, "event": "motor layout: 0"}, {"norm_timestamp": 0.9012370109558105, "event": "ball bounce"}, {"norm_timestamp": 0.9105510711669922, "event": "ball bounce"}, {"norm_timestamp": 0.9478819370269775, "event": "ball missed"}, {"norm_timestamp": 0.947882890701294, "event": "motor layout: 0"}, {"norm_timestamp": 0.9698407649993896, "event": "ball bounce"}, {"norm_timestamp": 1.0151560306549072, "event": "ball return"}, {"norm_timestamp": 1.0588300228118896, "event": "ball bounce"}, {"norm_timestamp": 1.1034088134765625, "event": "ball return"}, {"norm_timestamp": 1.1466319561004639, "event": "ball bounce"}, {"norm_timestamp": 1.189701795578003, "event": "ball return"}, {"norm_timestamp": 1.232301950454712, "event": "ball bounce"}, {"norm_timestamp": 1.248197078704834, "event": "ball bounce"}, {"norm_timestamp": 1.2750539779663086, "event": "ball return"}, {"norm_timestamp": 1.3181779384613037, "event": "ball bounce"}, {"norm_timestamp": 1.361137866973877, "event": "ball return"}, {"norm_timestamp": 1.4029030799865723, "event": "ball bounce"}, {"norm_timestamp": 1.4461979866027832, "event": "ball return"}, {"norm_timestamp": 1.4884748458862305, "event": "ball bounce"}, {"norm_timestamp": 1.5366778373718262, "event": "ball missed"}, {"norm_timestamp": 1.5366787910461426, "event": "motor layout: 0"}, {"norm_timestamp": 1.558790922164917, "event": "ball bounce"}, {"norm_timestamp": 1.5982129573822021, "event": "ball bounce"}, {"norm_timestamp": 1.6028368473052979, "event": "ball return"}, {"norm_timestamp": 1.6456689834594727, "event": "ball bounce"}, {"norm_timestamp": 1.6924090385437012, "event": "ball missed"}, {"norm_timestamp": 1.692411184310913, "event": "motor layout: 0"}, {"norm_timestamp": 1.7141599655151367, "event": "ball bounce"}, {"norm_timestamp": 1.7574899196624756, "event": "ball return"}, {"norm_timestamp": 1.800583839416504, "event": "ball bounce"}, {"norm_timestamp": 1.8414649963378906, "event": "ball bounce"}, {"norm_timestamp": 1.8438310623168945, "event": "ball return"}, {"norm_timestamp": 1.886981725692749, "event": "ball bounce"}, {"norm_timestamp": 1.9295258522033691, "event": "ball return"}, {"norm_timestamp": 1.9719948768615723, "event": "ball bounce"}, {"norm_timestamp": 2.02036190032959, "event": "ball missed"}, {"norm_timestamp": 2.0203628540039062, "event": "motor layout: 0"}, {"norm_timestamp": 2.042597770690918, "event": "ball bounce"}, {"norm_timestamp": 2.0541818141937256, "event": "ball bounce"}, {"norm_timestamp": 2.090472936630249, "event": "ball missed"}, {"norm_timestamp": 2.090474843978882, "event": "motor layout: 0"}, {"norm_timestamp": 2.112668991088867, "event": "ball bounce"}, {"norm_timestamp": 2.1286468505859375, "event": "ball bounce"}, {"norm_timestamp": 2.1558120250701904, "event": "ball return"}, {"norm_timestamp": 2.198342800140381, "event": "ball bounce"}, {"norm_timestamp": 2.2084977626800537, "event": "ball bounce"}, {"norm_timestamp": 2.244691848754883, "event": "ball missed"}, {"norm_timestamp": 2.2446930408477783, "event": "motor layout: 0"}, {"norm_timestamp": 2.266566753387451, "event": "ball bounce"}, {"norm_timestamp": 2.275484800338745, "event": "ball bounce"}, {"norm_timestamp": 2.313041925430298, "event": "ball missed"}, {"norm_timestamp": 2.3130438327789307, "event": "motor layout: 0"}, {"norm_timestamp": 2.334589958190918, "event": "ball bounce"}, {"norm_timestamp": 2.3781049251556396, "event": "ball return"}, {"norm_timestamp": 2.421168804168701, "event": "ball bounce"}, {"norm_timestamp": 2.463639974594116, "event": "ball return"}, {"norm_timestamp": 2.5067310333251953, "event": "ball bounce"}, {"norm_timestamp": 2.55073618888855, "event": "ball return"}, {"norm_timestamp": 2.5929861068725586, "event": "ball bounce"}, {"norm_timestamp": 2.608311891555786, "event": "ball bounce"}, {"norm_timestamp": 2.634305000305176, "event": "ball return"}, {"norm_timestamp": 2.6754589080810547, "event": "ball bounce"}, {"norm_timestamp": 2.7165448665618896, "event": "ball return"}, {"norm_timestamp": 2.757544994354248, "event": "ball bounce"}, {"norm_timestamp": 2.79880690574646, "event": "ball return"}, {"norm_timestamp": 2.839218854904175, "event": "ball bounce"}, {"norm_timestamp": 2.883976936340332, "event": "ball missed"}, {"norm_timestamp": 2.8839778900146484, "event": "motor layout: 0"}, {"norm_timestamp": 2.9046871662139893, "event": "ball bounce"}, {"norm_timestamp": 2.9460349082946777, "event": "ball return"}, {"norm_timestamp": 2.9787919521331787, "event": "ball bounce"}, {"norm_timestamp": 2.9876139163970947, "event": "ball bounce"}, {"norm_timestamp": 3.032240152359009, "event": "ball return"}, {"norm_timestamp": 3.075269937515259, "event": "ball bounce"}, {"norm_timestamp": 3.1205151081085205, "event": "ball missed"}, {"norm_timestamp": 3.1205170154571533, "event": "motor layout: 0"}, {"norm_timestamp": 3.1405999660491943, "event": "ball bounce"}, {"norm_timestamp": 3.181540012359619, "event": "ball return"}, {"norm_timestamp": 3.223176956176758, "event": "ball bounce"}, {"norm_timestamp": 3.264441967010498, "event": "ball return"}, {"norm_timestamp": 3.3061330318450928, "event": "ball bounce"}, {"norm_timestamp": 3.347287893295288, "event": "ball return"}, {"norm_timestamp": 3.3887670040130615, "event": "ball bounce"}, {"norm_timestamp": 3.403918981552124, "event": "ball bounce"}, {"norm_timestamp": 3.4304559230804443, "event": "ball return"}, {"norm_timestamp": 3.470982789993286, "event": "ball bounce"}, {"norm_timestamp": 3.5128698348999023, "event": "ball return"}, {"norm_timestamp": 3.556973934173584, "event": "ball bounce"}, {"norm_timestamp": 3.599421977996826, "event": "ball return"}, {"norm_timestamp": 3.641117811203003, "event": "ball bounce"}, {"norm_timestamp": 3.6825459003448486, "event": "ball return"}, {"norm_timestamp": 3.723604917526245, "event": "ball bounce"}, {"norm_timestamp": 3.7683699131011963, "event": "ball missed"}, {"norm_timestamp": 3.768371820449829, "event": "motor layout: 0"}, {"norm_timestamp": 3.7893660068511963, "event": "ball bounce"}, {"norm_timestamp": 3.830639123916626, "event": "ball return"}, {"norm_timestamp": 3.872220754623413, "event": "ball bounce"}, {"norm_timestamp": 3.9138128757476807, "event": "ball return"}, {"norm_timestamp": 3.955169916152954, "event": "ball bounce"}, {"norm_timestamp": 3.9963979721069336, "event": "ball return"}, {"norm_timestamp": 4.040566921234131, "event": "ball bounce"}, {"norm_timestamp": 4.056452035903931, "event": "ball bounce"}, {"norm_timestamp": 4.083414077758789, "event": "ball return"}, {"norm_timestamp": 4.125265836715698, "event": "ball bounce"}, {"norm_timestamp": 4.166889905929565, "event": "ball return"}, {"norm_timestamp": 4.208077907562256, "event": "ball bounce"}, {"norm_timestamp": 4.249804973602295, "event": "ball return"}, {"norm_timestamp": 4.290841102600098, "event": "ball bounce"}, {"norm_timestamp": 4.332830905914307, "event": "ball return"}, {"norm_timestamp": 4.375722885131836, "event": "ball bounce"}, {"norm_timestamp": 4.419992923736572, "event": "ball missed"}, {"norm_timestamp": 4.419994831085205, "event": "motor layout: 0"}, {"norm_timestamp": 4.4411351680755615, "event": "ball bounce"}, {"norm_timestamp": 4.451951026916504, "event": "ball bounce"}, {"norm_timestamp": 4.482239007949829, "event": "ball return"}, {"norm_timestamp": 4.52180290222168, "event": "ball bounce"}, {"norm_timestamp": 4.5249810218811035, "event": "ball bounce"}, {"norm_timestamp": 4.567766904830933, "event": "ball return"}, {"norm_timestamp": 4.592750072479248, "event": "ball bounce"}, {"norm_timestamp": 4.610702037811279, "event": "ball bounce"}, {"norm_timestamp": 4.655248165130615, "event": "ball missed"}, {"norm_timestamp": 4.655249834060669, "event": "motor layout: 0"}, {"norm_timestamp": 4.675867795944214, "event": "ball bounce"}, {"norm_timestamp": 4.716404914855957, "event": "ball return"}, {"norm_timestamp": 4.757053852081299, "event": "ball bounce"}, {"norm_timestamp": 4.800194978713989, "event": "ball missed"}, {"norm_timestamp": 4.800195932388306, "event": "motor layout: 0"}, {"norm_timestamp": 4.820257902145386, "event": "ball bounce"}, {"norm_timestamp": 4.859923839569092, "event": "ball return"}, {"norm_timestamp": 4.8693718910217285, "event": "ball bounce"}, {"norm_timestamp": 4.899800062179565, "event": "ball bounce"}, {"norm_timestamp": 4.942011833190918, "event": "ball missed"}, {"norm_timestamp": 4.942012786865234, "event": "motor layout: 0"}, {"norm_timestamp": 4.9621570110321045, "event": "ball bounce"}, {"norm_timestamp": 4.972616910934448, "event": "ball bounce"}, {"norm_timestamp": 5.004848003387451, "event": "ball missed"}, {"norm_timestamp": 5.004848957061768, "event": "motor layout: 0"}, {"norm_timestamp": 5.027026891708374, "event": "ball bounce"}, {"norm_timestamp": 5.037754058837891, "event": "ball bounce"}, {"norm_timestamp": 5.068790912628174, "event": "ball return"}, {"norm_timestamp": 5.106406927108765, "event": "ball bounce"}, {"norm_timestamp": 5.109709978103638, "event": "ball bounce"}, {"norm_timestamp": 5.150468111038208, "event": "ball return"}, {"norm_timestamp": 5.173414945602417, "event": "ball bounce"}, {"norm_timestamp": 5.190048933029175, "event": "ball bounce"}, {"norm_timestamp": 5.232586860656738, "event": "ball missed"}, {"norm_timestamp": 5.23258900642395, "event": "motor layout: 0"}, {"norm_timestamp": 5.252325057983398, "event": "ball bounce"}, {"norm_timestamp": 5.291813850402832, "event": "ball return"}, {"norm_timestamp": 5.3311238288879395, "event": "ball bounce"}, {"norm_timestamp": 5.368937015533447, "event": "ball bounce"}, {"norm_timestamp": 5.370949029922485, "event": "ball return"}, {"norm_timestamp": 5.41073203086853, "event": "ball bounce"}, {"norm_timestamp": 5.450225830078125, "event": "ball return"}, {"norm_timestamp": 5.48972487449646, "event": "ball bounce"}, {"norm_timestamp": 5.534179925918579, "event": "ball missed"}, {"norm_timestamp": 5.534181833267212, "event": "motor layout: 0"}, {"norm_timestamp": 5.554369926452637, "event": "ball bounce"}, {"norm_timestamp": 5.562519073486328, "event": "ball bounce"}, {"norm_timestamp": 5.5949718952178955, "event": "ball return"}, {"norm_timestamp": 5.62493896484375, "event": "ball bounce"}, {"norm_timestamp": 5.6353888511657715, "event": "ball bounce"}, {"norm_timestamp": 5.678221940994263, "event": "ball missed"}, {"norm_timestamp": 5.678224086761475, "event": "motor layout: 0"}, {"norm_timestamp": 5.697955131530762, "event": "ball bounce"}, {"norm_timestamp": 5.708454847335815, "event": "ball bounce"}, {"norm_timestamp": 5.737586975097656, "event": "ball return"}, {"norm_timestamp": 5.774205923080444, "event": "ball bounce"}, {"norm_timestamp": 5.77754807472229, "event": "ball bounce"}, {"norm_timestamp": 5.81719708442688, "event": "ball return"}, {"norm_timestamp": 5.840298891067505, "event": "ball bounce"}, {"norm_timestamp": 5.856964111328125, "event": "ball bounce"}, {"norm_timestamp": 5.904078960418701, "event": "ball missed"}, {"norm_timestamp": 5.904080152511597, "event": "motor layout: 0"}, {"norm_timestamp": 5.924437999725342, "event": "ball bounce"}, {"norm_timestamp": 5.964565992355347, "event": "ball return"}, {"norm_timestamp": 5.995830059051514, "event": "ball bounce"}, {"norm_timestamp": 6.004273891448975, "event": "ball bounce"}, {"norm_timestamp": 6.045593023300171, "event": "ball return"}, {"norm_timestamp": 6.085022926330566, "event": "ball bounce"}, {"norm_timestamp": 6.127147912979126, "event": "ball missed"}, {"norm_timestamp": 6.1271491050720215, "event": "motor layout: 0"}, {"norm_timestamp": 6.146809101104736, "event": "ball bounce"}, {"norm_timestamp": 6.1851561069488525, "event": "ball return"}, {"norm_timestamp": 6.2152698040008545, "event": "ball bounce"}, {"norm_timestamp": 6.223035097122192, "event": "ball bounce"}, {"norm_timestamp": 6.2614099979400635, "event": "ball return"}, {"norm_timestamp": 6.2996978759765625, "event": "ball bounce"}, {"norm_timestamp": 6.337658166885376, "event": "ball return"}, {"norm_timestamp": 6.376082897186279, "event": "ball bounce"}, {"norm_timestamp": 6.404094934463501, "event": "ball bounce"}, {"norm_timestamp": 6.415140151977539, "event": "ball return"}, {"norm_timestamp": 6.453819751739502, "event": "ball bounce"}, {"norm_timestamp": 6.492221832275391, "event": "ball return"}, {"norm_timestamp": 6.5307769775390625, "event": "ball bounce"}, {"norm_timestamp": 6.570352077484131, "event": "ball return"}, {"norm_timestamp": 6.595237731933594, "event": "ball bounce"}, {"norm_timestamp": 6.609830856323242, "event": "ball bounce"}, {"norm_timestamp": 6.648320913314819, "event": "ball return"}, {"norm_timestamp": 6.686383008956909, "event": "ball bounce"}, {"norm_timestamp": 6.727690935134888, "event": "ball missed"}, {"norm_timestamp": 6.727691888809204, "event": "motor layout: 0"}, {"norm_timestamp": 6.74680495262146, "event": "ball bounce"}, {"norm_timestamp": 6.772139072418213, "event": "ball bounce"}, {"norm_timestamp": 6.78515100479126, "event": "ball return"}, {"norm_timestamp": 6.823152780532837, "event": "ball bounce"}, {"norm_timestamp": 6.86399507522583, "event": "ball missed"}, {"norm_timestamp": 6.863995790481567, "event": "motor layout: 0"}, {"norm_timestamp": 6.882836818695068, "event": "ball bounce"}, {"norm_timestamp": 6.92132306098938, "event": "ball return"}, {"norm_timestamp": 6.959280014038086, "event": "ball bounce"}, {"norm_timestamp": 6.997533798217773, "event": "ball return"}, {"norm_timestamp": 7.037895917892456, "event": "ball bounce"}, {"norm_timestamp": 7.080688953399658, "event": "ball missed"}, {"norm_timestamp": 7.080689907073975, "event": "motor layout: 0"}, {"norm_timestamp": 7.100812911987305, "event": "ball bounce"}, {"norm_timestamp": 7.108834981918335, "event": "ball bounce"}, {"norm_timestamp": 7.1441309452056885, "event": "ball missed"}, {"norm_timestamp": 7.144132137298584, "event": "motor layout: 0"}, {"norm_timestamp": 7.16315484046936, "event": "ball bounce"}, {"norm_timestamp": 7.188219785690308, "event": "ball bounce"}, {"norm_timestamp": 7.204025983810425, "event": "ball missed"}, {"norm_timestamp": 7.20402717590332, "event": "motor layout: 0"}, {"norm_timestamp": 7.2231528759002686, "event": "ball bounce"}, {"norm_timestamp": 7.236932992935181, "event": "ball bounce"}, {"norm_timestamp": 7.2607879638671875, "event": "ball return"}, {"norm_timestamp": 7.298747777938843, "event": "ball bounce"}, {"norm_timestamp": 7.3078179359436035, "event": "ball bounce"}, {"norm_timestamp": 7.337671995162964, "event": "ball return"}, {"norm_timestamp": 7.375988960266113, "event": "ball bounce"}, {"norm_timestamp": 7.380128860473633, "event": "ball bounce"}, {"norm_timestamp": 7.414169073104858, "event": "ball return"}, {"norm_timestamp": 7.451613903045654, "event": "ball bounce"}, {"norm_timestamp": 7.452636957168579, "event": "ball bounce"}, {"norm_timestamp": 7.4903810024261475, "event": "ball return"}, {"norm_timestamp": 7.522502899169922, "event": "ball bounce"}, {"norm_timestamp": 7.528575897216797, "event": "ball bounce"}, {"norm_timestamp": 7.569275856018066, "event": "ball return"}, {"norm_timestamp": 7.596805095672607, "event": "ball bounce"}, {"norm_timestamp": 7.608163118362427, "event": "ball bounce"}, {"norm_timestamp": 7.6470770835876465, "event": "ball return"}, {"norm_timestamp": 7.6692869663238525, "event": "ball bounce"}, {"norm_timestamp": 7.685357093811035, "event": "ball bounce"}, {"norm_timestamp": 7.723810911178589, "event": "ball return"}, {"norm_timestamp": 7.741029739379883, "event": "ball bounce"}, {"norm_timestamp": 7.761937856674194, "event": "ball bounce"}, {"norm_timestamp": 7.8031511306762695, "event": "ball missed"}, {"norm_timestamp": 7.80315375328064, "event": "motor layout: 0"}, {"norm_timestamp": 7.822587013244629, "event": "ball bounce"}, {"norm_timestamp": 7.861116886138916, "event": "ball return"}, {"norm_timestamp": 7.899428129196167, "event": "ball bounce"}, {"norm_timestamp": 7.940500020980835, "event": "ball missed"}, {"norm_timestamp": 7.940500974655151, "event": "motor layout: 0"}, {"norm_timestamp": 7.959758043289185, "event": "ball bounce"}, {"norm_timestamp": 7.964767932891846, "event": "ball bounce"}, {"norm_timestamp": 7.998220920562744, "event": "ball return"}, {"norm_timestamp": 8.018663883209229, "event": "ball bounce"}, {"norm_timestamp": 8.04037094116211, "event": "ball bounce"}, {"norm_timestamp": 8.076228141784668, "event": "ball bounce"}, {"norm_timestamp": 8.086838960647583, "event": "ball missed"}, {"norm_timestamp": 8.0868399143219, "event": "motor layout: 0"}, {"norm_timestamp": 8.107873916625977, "event": "ball bounce"}, {"norm_timestamp": 8.14920687675476, "event": "ball return"}, {"norm_timestamp": 8.187865018844604, "event": "ball bounce"}, {"norm_timestamp": 8.226274967193604, "event": "ball return"}, {"norm_timestamp": 8.264829874038696, "event": "ball bounce"}, {"norm_timestamp": 8.303200960159302, "event": "ball return"}, {"norm_timestamp": 8.341395854949951, "event": "ball bounce"}, {"norm_timestamp": 8.382731914520264, "event": "ball missed"}, {"norm_timestamp": 8.38273310661316, "event": "motor layout: 0"}, {"norm_timestamp": 8.40186095237732, "event": "ball bounce"}, {"norm_timestamp": 8.440425872802734, "event": "ball return"}, {"norm_timestamp": 8.47920298576355, "event": "ball bounce"}, {"norm_timestamp": 8.520587921142578, "event": "ball missed"}, {"norm_timestamp": 8.52059006690979, "event": "motor layout: 0"}, {"norm_timestamp": 8.541152954101562, "event": "ball bounce"}, {"norm_timestamp": 8.551536083221436, "event": "ball bounce"}, {"norm_timestamp": 8.583701848983765, "event": "ball missed"}, {"norm_timestamp": 8.58370304107666, "event": "motor layout: 0"}, {"norm_timestamp": 8.603600025177002, "event": "ball bounce"}, {"norm_timestamp": 8.617816925048828, "event": "ball bounce"}, {"norm_timestamp": 8.645087957382202, "event": "ball missed"}, {"norm_timestamp": 8.645090103149414, "event": "motor layout: 0"}, {"norm_timestamp": 8.664944887161255, "event": "ball bounce"}, {"norm_timestamp": 8.673349857330322, "event": "ball bounce"}, {"norm_timestamp": 8.703882932662964, "event": "ball return"}, {"norm_timestamp": 8.73206090927124, "event": "ball bounce"}, {"norm_timestamp": 8.741643905639648, "event": "ball bounce"}, {"norm_timestamp": 8.781530141830444, "event": "ball missed"}, {"norm_timestamp": 8.781530857086182, "event": "motor layout: 0"}, {"norm_timestamp": 8.80000901222229, "event": "ball bounce"}, {"norm_timestamp": 8.807806968688965, "event": "ball bounce"}, {"norm_timestamp": 8.836993932723999, "event": "ball return"}, {"norm_timestamp": 8.864349842071533, "event": "ball bounce"}, {"norm_timestamp": 8.87398386001587, "event": "ball bounce"}, {"norm_timestamp": 8.910965919494629, "event": "ball return"}, {"norm_timestamp": 8.92078685760498, "event": "ball bounce"}, {"norm_timestamp": 8.94767689704895, "event": "ball bounce"}, {"norm_timestamp": 8.976310968399048, "event": "ball bounce"}, {"norm_timestamp": 8.984187126159668, "event": "ball return"}, {"norm_timestamp": 9.021353960037231, "event": "ball bounce"}, {"norm_timestamp": 9.03305697441101, "event": "ball bounce"}, {"norm_timestamp": 9.063644886016846, "event": "ball missed"}, {"norm_timestamp": 9.063645839691162, "event": "motor layout: 0"}, {"norm_timestamp": 9.082919836044312, "event": "ball bounce"}, {"norm_timestamp": 9.117321014404297, "event": "ball bounce"}, {"norm_timestamp": 9.124314785003662, "event": "ball missed"}, {"norm_timestamp": 9.124315738677979, "event": "motor layout: 0"}, {"norm_timestamp": 9.143045902252197, "event": "ball bounce"}, {"norm_timestamp": 9.183414936065674, "event": "ball missed"}, {"norm_timestamp": 9.183417081832886, "event": "motor layout: 0"}, {"norm_timestamp": 9.202166080474854, "event": "ball bounce"}, {"norm_timestamp": 9.209815979003906, "event": "ball bounce"}, {"norm_timestamp": 9.241581916809082, "event": "ball missed"}, {"norm_timestamp": 9.241583108901978, "event": "motor layout: 0"}, {"norm_timestamp": 9.241584062576294, "event": "ball return"}, {"norm_timestamp": 9.259835958480835, "event": "ball bounce"}, {"norm_timestamp": 9.299690961837769, "event": "ball missed"}, {"norm_timestamp": 9.299694061279297, "event": "motor layout: 0"}, {"norm_timestamp": 9.318209886550903, "event": "ball bounce"}, {"norm_timestamp": 9.325737953186035, "event": "ball bounce"}, {"norm_timestamp": 9.357829093933105, "event": "ball missed"}, {"norm_timestamp": 9.357829809188843, "event": "motor layout: 0"}, {"norm_timestamp": 9.35783076286316, "event": "ball return"}, {"norm_timestamp": 9.376099109649658, "event": "ball bounce"}, {"norm_timestamp": 9.389690160751343, "event": "ball bounce"}, {"norm_timestamp": 9.41609001159668, "event": "ball missed"}, {"norm_timestamp": 9.416091918945312, "event": "motor layout: 0"}, {"norm_timestamp": 9.434085845947266, "event": "ball bounce"}, {"norm_timestamp": 9.441744804382324, "event": "ball bounce"}, {"norm_timestamp": 9.473775148391724, "event": "ball missed"}, {"norm_timestamp": 9.473776817321777, "event": "motor layout: 0"}, {"norm_timestamp": 9.473776817321777, "event": "ball return"}, {"norm_timestamp": 9.492623090744019, "event": "ball bounce"}, {"norm_timestamp": 9.532389879226685, "event": "ball missed"}, {"norm_timestamp": 9.532391786575317, "event": "motor layout: 0"}, {"norm_timestamp": 9.552191019058228, "event": "ball bounce"}, {"norm_timestamp": 9.593163013458252, "event": "ball missed"}, {"norm_timestamp": 9.593163967132568, "event": "motor layout: 0"}, {"norm_timestamp": 9.611785888671875, "event": "ball bounce"}, {"norm_timestamp": 9.649225950241089, "event": "ball return"}, {"norm_timestamp": 9.685934066772461, "event": "ball bounce"}, {"norm_timestamp": 9.722386837005615, "event": "ball return"}, {"norm_timestamp": 9.75919795036316, "event": "ball bounce"}, {"norm_timestamp": 9.795963048934937, "event": "ball return"}, {"norm_timestamp": 9.832891941070557, "event": "ball bounce"}, {"norm_timestamp": 9.871377944946289, "event": "ball return"}, {"norm_timestamp": 9.884881973266602, "event": "ball bounce"}, {"norm_timestamp": 9.910052061080933, "event": "ball bounce"}, {"norm_timestamp": 9.949590921401978, "event": "ball return"}, {"norm_timestamp": 9.986013889312744, "event": "ball bounce"}, {"norm_timestamp": 10.022802829742432, "event": "ball return"}, {"norm_timestamp": 10.061946153640747, "event": "ball bounce"}, {"norm_timestamp": 10.100260972976685, "event": "ball return"}, {"norm_timestamp": 10.138338088989258, "event": "ball bounce"}, {"norm_timestamp": 10.178692102432251, "event": "ball missed"}, {"norm_timestamp": 10.178693056106567, "event": "motor layout: 0"}, {"norm_timestamp": 10.19709587097168, "event": "ball bounce"}, {"norm_timestamp": 10.236893892288208, "event": "ball missed"}, {"norm_timestamp": 10.236894845962524, "event": "motor layout: 0"}, {"norm_timestamp": 10.2554931640625, "event": "ball bounce"}, {"norm_timestamp": 10.295300006866455, "event": "ball missed"}, {"norm_timestamp": 10.295300960540771, "event": "motor layout: 0"}, {"norm_timestamp": 10.313678979873657, "event": "ball bounce"}, {"norm_timestamp": 10.338035821914673, "event": "ball bounce"}, {"norm_timestamp": 10.353746891021729, "event": "ball missed"}, {"norm_timestamp": 10.353749990463257, "event": "motor layout: 0"}, {"norm_timestamp": 10.372347116470337, "event": "ball bounce"}, {"norm_timestamp": 10.382016897201538, "event": "ball bounce"}, {"norm_timestamp": 10.411901950836182, "event": "ball missed"}, {"norm_timestamp": 10.411902904510498, "event": "motor layout: 0"}, {"norm_timestamp": 10.430583000183105, "event": "ball bounce"}, {"norm_timestamp": 10.438445091247559, "event": "ball bounce"}, {"norm_timestamp": 10.467581987380981, "event": "ball return"}, {"norm_timestamp": 10.495009899139404, "event": "ball bounce"}, {"norm_timestamp": 10.504787921905518, "event": "ball bounce"}, {"norm_timestamp": 10.54630994796753, "event": "ball missed"}, {"norm_timestamp": 10.546310901641846, "event": "motor layout: 0"}, {"norm_timestamp": 10.56524109840393, "event": "ball bounce"}, {"norm_timestamp": 10.575362920761108, "event": "ball bounce"}, {"norm_timestamp": 10.606238842010498, "event": "ball missed"}, {"norm_timestamp": 10.606240034103394, "event": "motor layout: 0"}, {"norm_timestamp": 10.625435829162598, "event": "ball bounce"}, {"norm_timestamp": 10.662796020507812, "event": "ball return"}, {"norm_timestamp": 10.699873924255371, "event": "ball bounce"}, {"norm_timestamp": 10.739489078521729, "event": "ball missed"}, {"norm_timestamp": 10.739490032196045, "event": "motor layout: 0"}, {"norm_timestamp": 10.758251905441284, "event": "ball bounce"}, {"norm_timestamp": 10.791115999221802, "event": "ball bounce"}, {"norm_timestamp": 10.797660827636719, "event": "ball missed"}, {"norm_timestamp": 10.797661781311035, "event": "motor layout: 0"}, {"norm_timestamp": 10.81652283668518, "event": "ball bounce"}, {"norm_timestamp": 10.856333017349243, "event": "ball missed"}, {"norm_timestamp": 10.85633397102356, "event": "motor layout: 0"}, {"norm_timestamp": 10.874433994293213, "event": "ball bounce"}, {"norm_timestamp": 10.88208293914795, "event": "ball bounce"}, {"norm_timestamp": 10.91401481628418, "event": "ball missed"}, {"norm_timestamp": 10.914016962051392, "event": "motor layout: 0"}, {"norm_timestamp": 10.914016962051392, "event": "ball return"}, {"norm_timestamp": 10.932652950286865, "event": "ball bounce"}, {"norm_timestamp": 10.951207876205444, "event": "ball bounce"}, {"norm_timestamp": 10.97260594367981, "event": "ball missed"}, {"norm_timestamp": 10.972606897354126, "event": "motor layout: 0"}, {"norm_timestamp": 10.9911208152771, "event": "ball bounce"}, {"norm_timestamp": 11.000837087631226, "event": "ball bounce"}, {"norm_timestamp": 11.030179977416992, "event": "ball return"}, {"norm_timestamp": 11.063987970352173, "event": "ball bounce"}, {"norm_timestamp": 11.0713369846344, "event": "ball bounce"}, {"norm_timestamp": 11.112230777740479, "event": "ball missed"}, {"norm_timestamp": 11.112231969833374, "event": "motor layout: 0"}, {"norm_timestamp": 11.131131887435913, "event": "ball bounce"}, {"norm_timestamp": 11.171135902404785, "event": "ball missed"}, {"norm_timestamp": 11.171138048171997, "event": "motor layout: 0"}, {"norm_timestamp": 11.18973994255066, "event": "ball bounce"}, {"norm_timestamp": 11.226070880889893, "event": "ball return"}, {"norm_timestamp": 11.26188588142395, "event": "ball bounce"}, {"norm_timestamp": 11.297552108764648, "event": "ball return"}, {"norm_timestamp": 11.332890748977661, "event": "ball bounce"}, {"norm_timestamp": 11.368864059448242, "event": "ball return"}, {"norm_timestamp": 11.404624938964844, "event": "ball bounce"}, {"norm_timestamp": 11.439857959747314, "event": "ball return"}, {"norm_timestamp": 11.455129146575928, "event": "ball bounce"}, {"norm_timestamp": 11.475526809692383, "event": "ball bounce"}, {"norm_timestamp": 11.510771989822388, "event": "ball return"}, {"norm_timestamp": 11.546092987060547, "event": "ball bounce"}, {"norm_timestamp": 11.58394193649292, "event": "ball return"}, {"norm_timestamp": 11.620773077011108, "event": "ball bounce"}, {"norm_timestamp": 11.657179832458496, "event": "ball return"}, {"norm_timestamp": 11.692644119262695, "event": "ball bounce"}, {"norm_timestamp": 11.730791807174683, "event": "ball missed"}, {"norm_timestamp": 11.730792999267578, "event": "motor layout: 0"}, {"norm_timestamp": 11.74835205078125, "event": "ball bounce"}, {"norm_timestamp": 11.780117988586426, "event": "ball bounce"}, {"norm_timestamp": 11.786756038665771, "event": "ball missed"}, {"norm_timestamp": 11.786756992340088, "event": "motor layout: 0"}, {"norm_timestamp": 11.804791927337646, "event": "ball bounce"}, {"norm_timestamp": 11.817776918411255, "event": "ball bounce"}, {"norm_timestamp": 11.84292984008789, "event": "ball missed"}, {"norm_timestamp": 11.842930793762207, "event": "motor layout: 0"}, {"norm_timestamp": 11.861210823059082, "event": "ball bounce"}, {"norm_timestamp": 11.893646955490112, "event": "ball bounce"}, {"norm_timestamp": 11.900231838226318, "event": "ball missed"}, {"norm_timestamp": 11.900232791900635, "event": "motor layout: 0"}, {"norm_timestamp": 11.918617010116577, "event": "ball bounce"}, {"norm_timestamp": 11.957061767578125, "event": "ball missed"}, {"norm_timestamp": 11.95706295967102, "event": "motor layout: 0"}, {"norm_timestamp": 11.975164890289307, "event": "ball bounce"}, {"norm_timestamp": 12.013143062591553, "event": "ball missed"}, {"norm_timestamp": 12.01314401626587, "event": "motor layout: 0"}, {"norm_timestamp": 12.031049013137817, "event": "ball bounce"}, {"norm_timestamp": 12.072425842285156, "event": "ball missed"}, {"norm_timestamp": 12.072427034378052, "event": "motor layout: 0"}, {"norm_timestamp": 12.090812921524048, "event": "ball bounce"}, {"norm_timestamp": 12.10062575340271, "event": "ball bounce"}, {"norm_timestamp": 12.130847930908203, "event": "ball missed"}, {"norm_timestamp": 12.13084888458252, "event": "motor layout: 0"}, {"norm_timestamp": 12.149249076843262, "event": "ball bounce"}, {"norm_timestamp": 12.18716287612915, "event": "ball missed"}, {"norm_timestamp": 12.187164783477783, "event": "motor layout: 0"}]